dotbak/__init__.py
dotbak/main.py
dotbak/controllers/__init__.py
dotbak/controllers/base.py
dotbak/core/__init__.py
dotbak/core/exc.py
dotbak/core/version.py
dotbak/ext/__init__.py
dotbak/plugins/__init__.py
dotbak/templates/__init__.py
dotbak-0.0.6b0.dist-info/LICENSE
dotbak-0.0.6b0.dist-info/METADATA
dotbak-0.0.6b0.dist-info/WHEEL
dotbak-0.0.6b0.dist-info/entry_points.txt
dotbak-0.0.6b0.dist-info/top_level.txt
dotbak-0.0.6b0.dist-info/RECORD
