Metadata-Version: 2.1
Name: dotbak
Version: 0.0.6b0
Summary: Lazily Backup Files and Directories
Home-page: https://github.com/datafolklabs/dotbak
Author: BJ Dierkes
Author-email: derks@datafolklabs.com
License: BSD (three-clause)
Platform: UNKNOWN
License-File: LICENSE
